conda_index/__init__.py
conda_index/__main__.py
conda_index/_version.py
conda_index/api.py
conda_index/json2jlap.py
conda_index/plugin.py
conda_index/utils.py
conda_index/utils_build.py
conda_index/yaml.py
conda_index/cli/__init__.py
conda_index/index/__init__.py
conda_index/index/cache.py
conda_index/index/common.py
conda_index/index/convert_cache.py
conda_index/index/current_repodata.py
conda_index/index/fs.py
conda_index/index/logutil.py
conda_index/index/rss.py
conda_index/index/sqlitecache.py
conda_index/postgres/cache.py
conda_index/postgres/model.py
conda_index/templates/channeldata-index.html.j2
conda_index/templates/subdir-index.html.j2
conda_index-0.7.0.dist-info/METADATA
conda_index-0.7.0.dist-info/WHEEL
conda_index-0.7.0.dist-info/entry_points.txt
conda_index-0.7.0.dist-info/licenses/AUTHORS.md
conda_index-0.7.0.dist-info/licenses/LICENSE
conda_index-0.7.0.dist-info/RECORD
