Metadata-Version: 2.4
Name: conda_index
Version: 0.7.0
Dynamic: Summary
Project-URL: Home, https://github.com/conda/conda-index
Author-email: "Anaconda, Inc. & Contributors" <conda@continuum.io>
License: BSD 3-Clause License
License-File: AUTHORS.md
License-File: LICENSE
Requires-Python: >=3.8
Requires-Dist: click>=8
Requires-Dist: conda-package-streaming>=0.7.0
Requires-Dist: filelock
Requires-Dist: jinja2
Requires-Dist: msgpack
Requires-Dist: ruamel-yaml
Requires-Dist: zstandard
Provides-Extra: docs
Requires-Dist: furo; extra == 'docs'
Requires-Dist: mdit-py-plugins>=0.3.0; extra == 'docs'
Requires-Dist: myst-parser; extra == 'docs'
Requires-Dist: sphinx; extra == 'docs'
Requires-Dist: sphinx-click; extra == 'docs'
Provides-Extra: test
Requires-Dist: conda-build>=3.21.0; extra == 'test'
Requires-Dist: conda-package-handling>=1.9.0; extra == 'test'
Requires-Dist: coverage[toml]; extra == 'test'
Requires-Dist: fsspec[http]; extra == 'test'
Requires-Dist: pytest-cov; extra == 'test'
Requires-Dist: pytest-mock; extra == 'test'
Requires-Dist: pytest>=7; extra == 'test'
